cfspflat/__init__.py
cfspflat/cf_dns.py
cfspflat/cli.py
cfspflat-24.12.17.data/scripts/cfspflat
cfspflat-24.12.17.dist-info/LICENSE.txt
cfspflat-24.12.17.dist-info/METADATA
cfspflat-24.12.17.dist-info/WHEEL
cfspflat-24.12.17.dist-info/top_level.txt
cfspflat-24.12.17.dist-info/RECORD
