Metadata-Version: 2.1
Name: cfspflat
Version: 24.12.17
Summary: Flattens SPF records and updates Cloudflare zones
Home-page: https://github.com/Glocktober/cfspflat
Author: gunville
Author-email: rk13088@yahoo.com
Project-URL: repo, https://github.com/Glocktober/cfspflat.git
Project-URL: overview, https://github.com/Glocktober/cfspflat/blob/master/README.md
Keywords: 'cloudflare dns spf'
Classifier: Programming Language :: Python :: 3
Classifier: License :: OSI Approved :: MIT License
Classifier: Operating System :: OS Independent
Requires-Python: >=3.7
License-File: LICENSE.txt
Requires-Dist: cloudflare>=3.1
Requires-Dist: sender-policy-flattener==0.3.1
